kimg4/__init__.py
kimg4/asn1.py
kimg4/img4.py
kimg4-0.1.1.dist-info/METADATA
kimg4-0.1.1.dist-info/WHEEL
kimg4-0.1.1.dist-info/top_level.txt
kimg4-0.1.1.dist-info/RECORD
