Metadata-Version: 2.1
Name: kimg4
Version: 0.1.1
Summary: pure-python library for parsing/decrypting Apple's proprietary IMG4 format.
Home-page: https://github.com/kritantadev/kimg4
Author: kritanta
License: UNKNOWN
Platform: UNKNOWN
Classifier: Programming Language :: Python :: 3
Classifier: License :: OSI Approved :: MIT License
Classifier: Operating System :: OS Independent
Requires-Dist: pyaes
